signal_protocol-0.2.3.dist-info/RECORD
signal_protocol-0.2.3.dist-info/top_level.txt
signal_protocol-0.2.3.dist-info/METADATA
signal_protocol-0.2.3.dist-info/WHEEL
signal_protocol-0.2.3.dist-info/LICENSE
signal_protocol/__init__.py
signal_protocol/signal_protocol.cpython-37m-x86_64-linux-gnu.so
signal_protocol/signal_protocol.cpython-39-x86_64-linux-gnu.so
signal_protocol/signal_protocol.cpython-38-x86_64-linux-gnu.so
signal_protocol/signal_protocol.cpython-36m-x86_64-linux-gnu.so
