Metadata-Version: 2.1
Name: signal-protocol
Version: 0.2.3
Summary: Rust extension providing Python bindings to the signal protocol
Home-page: UNKNOWN
License: UNKNOWN
Platform: UNKNOWN
Classifier: License :: OSI Approved :: GNU Affero General Public License v3 or later (AGPLv3+)
Classifier: Development Status :: 3 - Alpha
Classifier: Intended Audience :: Developers
Classifier: Programming Language :: Python
Classifier: Programming Language :: Rust
License-File: LICENSE
